{"configurations": {"count": 35, "items": {"K1": {"index": 0, "setupTimes": [0, 6, 6, 3, 9, 6, 10, 5, 8, 3, 10, 10, 6, 9, 6, 10, 3, 6, 5, 2, 9, 4, 3, 2, 10, 9, 4, 9, 10, 5, 7, 3, 10, 3, 10]}, "K2": {"index": 1, "setupTimes": [6, 0, 6, 6, 9, 7, 3, 3, 9, 2, 7, 5, 2, 8, 9, 6, 5, 9, 4, 9, 2, 7, 10, 4, 9, 6, 8, 7, 6, 5, 3, 3, 5, 6, 3]}, "K3": {"index": 2, "setupTimes": [2, 5, 0, 4, 7, 6, 4, 4, 2, 3, 10, 4, 9, 4, 8, 9, 10, 4, 7, 8, 4, 7, 8, 9, 3, 7, 9, 4, 3, 6, 9, 7, 3, 6, 3]}, "K4": {"index": 3, "setupTimes": [10, 2, 7, 0, 4, 5, 9, 3, 9, 6, 2, 2, 3, 3, 7, 5, 5, 2, 8, 8, 2, 2, 6, 5, 3, 10, 10, 6, 9, 2, 7, 3, 3, 9, 7]}, "K5": {"index": 4, "setupTimes": [3, 9, 4, 5, 0, 3, 2, 6, 4, 6, 7, 9, 10, 6, 5, 5, 3, 3, 9, 8, 8, 8, 5, 9, 10, 2, 5, 10, 2, 9, 4, 10, 2, 9, 6]}, "K6": {"index": 5, "setupTimes": [3, 5, 7, 8, 2, 0, 3, 6, 9, 8, 3, 2, 2, 5, 10, 8, 6, 4, 5, 2, 6, 10, 6, 7, 9, 2, 6, 4, 3, 2, 5, 3, 8, 2, 8]}, "K7": {"index": 6, "setupTimes": [5, 2, 9, 3, 7, 10, 0, 2, 4, 10, 7, 5, 10, 6, 9, 10, 3, 2, 7, 4, 7, 9, 10, 4, 10, 6, 5, 10, 5, 7, 3, 10, 5, 6, 10]}, "K8": {"index": 7, "setupTimes": [2, 8, 4, 10, 2, 5, 10, 0, 3, 9, 9, 5, 2, 5, 10, 10, 5, 5, 10, 5, 3, 10, 4, 10, 5, 3, 10, 7, 2, 7, 4, 5, 6, 3, 2]}, "K9": {"index": 8, "setupTimes": [9, 8, 3, 4, 7, 9, 9, 8, 0, 6, 2, 10, 4, 10, 6, 9, 7, 7, 5, 6, 2, 4, 9, 2, 2, 2, 2, 6, 8, 2, 2, 8, 3, 10, 7]}, "K10": {"index": 9, "setupTimes": [2, 9, 2, 6, 2, 6, 9, 3, 9, 0, 9, 9, 8, 3, 8, 9, 4, 6, 5, 8, 8, 7, 7, 2, 6, 4, 9, 7, 6, 6, 7, 5, 4, 6, 6]}, "K11": {"index": 10, "setupTimes": [9, 8, 7, 6, 10, 8, 4, 5, 5, 7, 0, 10, 6, 10, 2, 4, 5, 4, 9, 4, 2, 3, 3, 3, 10, 8, 5, 7, 10, 5, 5, 6, 6, 5, 8]}, "K12": {"index": 11, "setupTimes": [3, 10, 5, 2, 5, 4, 6, 7, 6, 4, 8, 0, 9, 9, 5, 10, 6, 5, 2, 4, 7, 7, 5, 9, 3, 4, 5, 8, 7, 3, 10, 9, 4, 2, 3]}, "K13": {"index": 12, "setupTimes": [4, 4, 6, 8, 2, 6, 10, 9, 2, 4, 5, 6, 0, 8, 8, 3, 5, 7, 5, 3, 2, 3, 6, 4, 4, 10, 3, 7, 7, 8, 6, 6, 3, 4, 9]}, "K14": {"index": 13, "setupTimes": [9, 6, 9, 6, 5, 10, 6, 3, 6, 9, 2, 8, 5, 0, 3, 5, 4, 7, 2, 10, 10, 9, 2, 2, 8, 6, 6, 2, 7, 7, 4, 5, 5, 3, 9]}, "K15": {"index": 14, "setupTimes": [4, 2, 2, 4, 8, 8, 2, 2, 10, 4, 5, 3, 9, 2, 0, 3, 9, 3, 6, 8, 4, 7, 5, 5, 5, 2, 7, 6, 3, 2, 7, 2, 2, 7, 4]}, "K16": {"index": 15, "setupTimes": [6, 9, 3, 10, 10, 5, 6, 2, 9, 2, 7, 4, 5, 5, 8, 0, 6, 5, 6, 6, 10, 10, 10, 10, 7, 2, 6, 4, 6, 3, 4, 10, 9, 5, 7]}, "K17": {"index": 16, "setupTimes": [2, 5, 2, 3, 2, 10, 6, 9, 8, 5, 10, 10, 3, 6, 6, 8, 0, 8, 4, 4, 8, 9, 9, 10, 10, 2, 8, 9, 2, 2, 3, 7, 9, 7, 4]}, "K18": {"index": 17, "setupTimes": [7, 7, 7, 8, 2, 6, 9, 3, 7, 7, 10, 9, 6, 2, 9, 4, 2, 0, 3, 10, 2, 3, 8, 8, 2, 3, 6, 2, 2, 7, 10, 10, 8, 9, 4]}, "K19": {"index": 18, "setupTimes": [2, 5, 8, 7, 3, 8, 4, 9, 4, 9, 9, 7, 2, 7, 2, 7, 6, 10, 0, 2, 9, 2, 6, 10, 7, 5, 8, 4, 4, 5, 5, 9, 2, 7, 8]}, "K20": {"index": 19, "setupTimes": [7, 9, 9, 7, 9, 2, 7, 10, 4, 7, 5, 8, 5, 4, 6, 6, 10, 10, 6, 0, 2, 9, 10, 7, 2, 8, 2, 10, 8, 8, 10, 4, 8, 7, 4]}, "K21": {"index": 20, "setupTimes": [4, 6, 2, 6, 3, 7, 2, 2, 10, 5, 10, 6, 7, 5, 5, 8, 8, 2, 9, 3, 0, 4, 7, 5, 2, 2, 4, 8, 7, 8, 6, 7, 2, 5, 2]}, "K22": {"index": 21, "setupTimes": [3, 2, 10, 2, 10, 2, 7, 2, 8, 10, 8, 6, 5, 8, 10, 8, 5, 4, 3, 8, 4, 0, 9, 5, 10, 2, 5, 10, 6, 7, 2, 3, 6, 9, 5]}, "K23": {"index": 22, "setupTimes": [3, 8, 6, 8, 9, 9, 7, 6, 4, 7, 3, 10, 4, 7, 6, 10, 2, 3, 9, 5, 4, 7, 0, 4, 3, 4, 4, 6, 10, 7, 4, 2, 10, 9, 9]}, "K24": {"index": 23, "setupTimes": [3, 9, 3, 2, 6, 2, 2, 4, 8, 4, 2, 2, 6, 3, 4, 6, 5, 9, 3, 4, 4, 4, 4, 0, 7, 7, 5, 2, 10, 5, 6, 7, 3, 6, 9]}, "K25": {"index": 24, "setupTimes": [8, 8, 7, 3, 2, 7, 8, 8, 5, 2, 9, 8, 4, 2, 6, 4, 4, 2, 9, 3, 7, 9, 2, 4, 0, 9, 5, 6, 3, 9, 5, 6, 3, 3, 9]}, "K26": {"index": 25, "setupTimes": [10, 7, 8, 2, 2, 2, 4, 7, 4, 3, 9, 7, 8, 6, 6, 7, 6, 8, 5, 7, 3, 3, 8, 10, 9, 0, 3, 2, 7, 6, 10, 4, 8, 8, 4]}, "K27": {"index": 26, "setupTimes": [5, 6, 5, 9, 2, 2, 9, 3, 7, 6, 2, 5, 2, 6, 3, 5, 7, 10, 6, 8, 2, 9, 2, 4, 8, 9, 0, 8, 8, 4, 9, 8, 5, 8, 7]}, "K28": {"index": 27, "setupTimes": [9, 2, 3, 8, 3, 8, 10, 7, 4, 7, 9, 8, 2, 9, 6, 8, 2, 7, 6, 7, 6, 7, 10, 9, 5, 3, 4, 0, 9, 7, 2, 2, 8, 2, 5]}, "K29": {"index": 28, "setupTimes": [9, 6, 9, 7, 8, 2, 8, 5, 5, 7, 8, 10, 2, 7, 10, 8, 5, 3, 7, 4, 7, 9, 5, 5, 6, 3, 6, 9, 0, 6, 10, 4, 8, 2, 2]}, "K30": {"index": 29, "setupTimes": [2, 7, 10, 6, 10, 9, 6, 8, 8, 6, 5, 5, 5, 5, 4, 9, 2, 9, 10, 4, 10, 7, 10, 2, 9, 2, 10, 6, 10, 0, 10, 9, 10, 8, 6]}, "K31": {"index": 30, "setupTimes": [4, 3, 4, 8, 5, 5, 2, 2, 5, 3, 4, 6, 2, 2, 8, 5, 8, 2, 6, 4, 10, 7, 10, 10, 2, 6, 8, 4, 6, 7, 0, 6, 3, 7, 3]}, "K32": {"index": 31, "setupTimes": [5, 3, 10, 6, 4, 7, 6, 9, 3, 7, 10, 7, 10, 2, 7, 8, 9, 6, 6, 10, 3, 4, 5, 8, 7, 8, 8, 9, 8, 2, 5, 0, 4, 8, 2]}, "K33": {"index": 32, "setupTimes": [7, 6, 3, 2, 4, 4, 9, 3, 8, 4, 3, 9, 9, 5, 6, 4, 9, 8, 10, 9, 4, 9, 10, 7, 5, 10, 6, 8, 8, 2, 8, 5, 0, 2, 7]}, "K34": {"index": 33, "setupTimes": [8, 7, 9, 5, 10, 5, 4, 7, 6, 8, 5, 4, 3, 3, 7, 4, 10, 8, 3, 10, 9, 8, 6, 9, 6, 4, 9, 9, 8, 6, 6, 2, 5, 0, 3]}, "K35": {"index": 34, "setupTimes": [4, 3, 9, 5, 8, 5, 3, 5, 8, 3, 5, 6, 7, 2, 4, 8, 2, 2, 7, 6, 6, 4, 4, 3, 3, 7, 5, 3, 6, 6, 7, 4, 10, 9, 0]}}}, "testers": {"count": 196, "items": {"T1": {"supportedConfigurations": ["K34", "K14", "K21", "K7", "K2", "K18", "K1", "K35", "K28", "K4", "K27", "K9", "K26", "K23", "K15", "K31", "K22", "K20", "K30", "K13", "K11"]}, "T2": {"supportedConfigurations": ["K13", "K26", "K24", "K33", "K6", "K31", "K7", "K1", "K16", "K17", "K19", "K11"]}, "T3": {"supportedConfigurations": ["K29", "K20", "K30", "K11", "K8", "K21", "K32", "K6", "K13", "K5", "K31"]}, "T4": {"supportedConfigurations": ["K16", "K18", "K1", "K2", "K24", "K5", "K23"]}, "T5": {"supportedConfigurations": ["K4", "K19", "K10", "K22", "K20"]}, "T6": {"supportedConfigurations": ["K1", "K11", "K12", "K23", "K6", "K25", "K7", "K22", "K28", "K4", "K5", "K14", "K15", "K29", "K30", "K24", "K13", "K8", "K18", "K32", "K33"]}, "T7": {"supportedConfigurations": ["K9", "K35", "K32", "K25", "K23", "K20", "K33", "K4", "K10", "K31", "K26", "K11", "K21"]}, "T8": {"supportedConfigurations": ["K1", "K35", "K13"]}, "T9": {"supportedConfigurations": ["K22", "K26", "K16", "K18", "K27", "K1", "K34", "K13", "K3", "K31", "K5", "K9", "K21", "K20", "K6", "K28", "K11", "K32", "K35", "K33", "K17"]}, "T10": {"supportedConfigurations": ["K19", "K34", "K21"]}, "T11": {"supportedConfigurations": ["K21", "K29", "K7", "K8", "K11", "K28", "K2", "K19", "K25", "K26", "K3", "K18", "K24", "K4", "K20", "K12"]}, "T12": {"supportedConfigurations": ["K13", "K9", "K34", "K27", "K15", "K21", "K33", "K3", "K25", "K20", "K2", "K23", "K12", "K17", "K4", "K10", "K1", "K16", "K35", "K5", "K8", "K29", "K30", "K11", "K22", "K32", "K7", "K14", "K28", "K31", "K26", "K6"]}, "T13": {"supportedConfigurations": ["K9", "K31", "K19", "K14"]}, "T14": {"supportedConfigurations": ["K19", "K1", "K14", "K8", "K10"]}, "T15": {"supportedConfigurations": ["K28", "K16", "K22", "K17", "K6", "K19", "K7", "K24", "K10", "K32", "K12", "K15", "K30", "K18", "K2", "K3", "K23", "K27", "K25", "K26", "K29", "K34", "K9"]}, "T16": {"supportedConfigurations": ["K23", "K11", "K26", "K13", "K31", "K27", "K14", "K18", "K5", "K17"]}, "T17": {"supportedConfigurations": ["K18", "K22", "K7", "K5", "K13", "K26", "K23", "K10", "K3", "K11", "K15", "K33", "K16", "K29", "K21", "K19", "K34", "K2", "K12", "K9", "K27", "K4", "K31", "K17", "K20", "K30", "K14", "K35", "K32", "K25", "K1", "K6", "K28"]}, "T18": {"supportedConfigurations": ["K1", "K28", "K19", "K8", "K23", "K21", "K17", "K27", "K29", "K25", "K3", "K2", "K32", "K5", "K16", "K13", "K35", "K11", "K34", "K22", "K6", "K14", "K10", "K30", "K7"]}, "T19": {"supportedConfigurations": ["K27", "K14", "K17", "K26", "K30", "K23", "K25", "K24", "K7", "K20", "K33", "K5", "K9", "K32", "K34", "K15", "K11", "K3", "K19"]}, "T20": {"supportedConfigurations": ["K21", "K3", "K19", "K29", "K34", "K15", "K4", "K8", "K14", "K7"]}, "T21": {"supportedConfigurations": ["K1", "K22", "K34", "K30", "K17", "K12", "K33"]}, "T22": {"supportedConfigurations": ["K6", "K35", "K20", "K25", "K11", "K7", "K32", "K16", "K29", "K34", "K2", "K12", "K15", "K3"]}, "T23": {"supportedConfigurations": ["K32", "K7", "K30", "K17", "K21", "K18", "K35", "K29", "K31", "K26", "K28", "K4", "K13", "K10", "K25", "K8"]}, "T24": {"supportedConfigurations": ["K2", "K8", "K29", "K17", "K4", "K13"]}, "T25": {"supportedConfigurations": ["K29", "K9", "K24", "K8", "K15", "K14", "K35", "K16"]}, "T26": {"supportedConfigurations": ["K14", "K1", "K28", "K25", "K32", "K24", "K17", "K30", "K7", "K15", "K2", "K8"]}, "T27": {"supportedConfigurations": ["K27", "K3", "K9", "K1", "K17", "K2"]}, "T28": {"supportedConfigurations": ["K35", "K19", "K34", "K27", "K13", "K2", "K32", "K7"]}, "T29": {"supportedConfigurations": ["K25", "K26", "K9", "K17", "K13", "K16", "K6", "K11", "K12", "K32", "K21"]}, "T30": {"supportedConfigurations": ["K29", "K33", "K1", "K4", "K24", "K3", "K11", "K21", "K31", "K32", "K15", "K23", "K25", "K16", "K35", "K2", "K8", "K18", "K17", "K30", "K34", "K12", "K9", "K27"]}, "T31": {"supportedConfigurations": ["K14", "K30", "K35", "K28", "K32", "K33", "K8", "K18", "K20", "K21", "K19", "K11", "K5", "K31", "K13", "K1", "K16", "K15", "K26", "K24", "K10", "K3", "K7", "K29", "K9", "K6", "K34", "K17", "K12", "K27", "K22", "K25", "K23"]}, "T32": {"supportedConfigurations": ["K26", "K8", "K1", "K13", "K27", "K33", "K18", "K15", "K11", "K16", "K25", "K14", "K6"]}, "T33": {"supportedConfigurations": ["K4", "K7", "K21", "K2", "K19", "K25", "K32", "K10", "K29", "K5", "K30", "K6", "K17", "K34", "K28", "K27", "K26", "K31", "K11", "K13", "K8"]}, "T34": {"supportedConfigurations": ["K13", "K22", "K33"]}, "T35": {"supportedConfigurations": ["K15", "K7", "K27", "K21", "K11", "K26", "K1"]}, "T36": {"supportedConfigurations": ["K16", "K19", "K30", "K20", "K2", "K6", "K18", "K1", "K8", "K29", "K34", "K17", "K5", "K3"]}, "T37": {"supportedConfigurations": ["K7", "K8", "K16", "K4", "K22", "K35", "K23", "K26", "K3", "K29", "K12", "K19", "K32", "K33", "K14", "K27", "K2", "K31", "K17", "K1", "K24", "K11", "K10", "K34"]}, "T38": {"supportedConfigurations": ["K14", "K29"]}, "T39": {"supportedConfigurations": ["K2", "K8", "K22", "K3", "K16", "K24", "K20", "K19", "K11"]}, "T40": {"supportedConfigurations": ["K7", "K13", "K25", "K16", "K35", "K6", "K11", "K33", "K15", "K14", "K17", "K21", "K26", "K23", "K29", "K19", "K3", "K5", "K1", "K28", "K20", "K32"]}, "T41": {"supportedConfigurations": ["K20", "K3", "K33", "K31", "K9", "K28", "K8", "K27", "K17", "K19", "K30", "K25", "K14", "K16", "K6", "K15", "K5", "K22", "K34", "K2", "K4", "K29", "K18", "K11", "K7", "K23", "K13", "K1", "K10", "K12", "K35", "K21"]}, "T42": {"supportedConfigurations": ["K33", "K11", "K4", "K17", "K16", "K8", "K10", "K34"]}, "T43": {"supportedConfigurations": ["K10", "K14", "K6", "K23", "K25", "K13", "K18", "K4", "K7", "K22", "K28", "K21", "K31", "K24", "K29", "K33", "K8", "K19", "K32", "K35", "K2", "K30", "K12", "K16", "K17", "K34", "K26", "K5", "K3", "K15", "K9", "K20", "K1"]}, "T44": {"supportedConfigurations": ["K4", "K8", "K17", "K5", "K26", "K28", "K34"]}, "T45": {"supportedConfigurations": ["K5", "K8", "K3", "K2", "K19", "K4", "K10", "K34", "K6", "K26", "K17", "K28"]}, "T46": {"supportedConfigurations": ["K30", "K19", "K4", "K1", "K21", "K22", "K26", "K28", "K27", "K5", "K7", "K24", "K25", "K15", "K12", "K10"]}, "T47": {"supportedConfigurations": ["K20", "K18", "K26", "K12", "K24", "K4", "K29", "K31"]}, "T48": {"supportedConfigurations": ["K23", "K14", "K35", "K25", "K32", "K21", "K17", "K24", "K6", "K3", "K11", "K19", "K16", "K13", "K4", "K31", "K28", "K34", "K27", "K7", "K18", "K15"]}, "T49": {"supportedConfigurations": ["K15", "K25", "K33", "K10", "K22", "K11", "K12", "K19", "K8"]}, "T50": {"supportedConfigurations": ["K21", "K8", "K25", "K22", "K30", "K10", "K13", "K6", "K27", "K3", "K9", "K1", "K7", "K11", "K35", "K32", "K18", "K20", "K12", "K4", "K17", "K14", "K33", "K2", "K19", "K29", "K15", "K16", "K23", "K31", "K28", "K26", "K5"]}, "T51": {"supportedConfigurations": ["K9", "K1", "K17", "K34", "K33", "K28", "K14", "K22", "K24", "K13", "K20", "K27", "K15", "K35", "K25", "K12", "K3", "K7", "K29", "K8", "K19", "K11", "K32", "K31", "K23", "K16", "K10", "K6", "K26", "K30", "K2", "K21", "K5", "K4", "K18"]}, "T52": {"supportedConfigurations": ["K26", "K24", "K6", "K2", "K5", "K4", "K17", "K16", "K23", "K27", "K20", "K9", "K13", "K22", "K33", "K8", "K3", "K32", "K29", "K7", "K28", "K14", "K31", "K12", "K25", "K11", "K18", "K1", "K34", "K35"]}, "T53": {"supportedConfigurations": ["K6", "K10", "K21", "K2", "K27", "K34", "K33", "K9", "K11", "K3", "K32", "K20", "K13", "K14", "K1", "K24", "K7", "K17", "K5", "K8", "K4", "K16", "K22", "K29", "K15", "K23", "K26", "K19", "K31", "K25", "K18", "K35", "K28", "K12", "K30"]}, "T54": {"supportedConfigurations": ["K4", "K18", "K12", "K9", "K19", "K1", "K31", "K34", "K5", "K24", "K35", "K7", "K17", "K11", "K6", "K3", "K15", "K29", "K28", "K33", "K23", "K26", "K21", "K2", "K25"]}, "T55": {"supportedConfigurations": ["K19", "K31", "K17", "K6", "K20", "K9", "K24", "K4", "K27", "K34", "K5", "K7", "K13", "K35", "K22", "K28", "K26"]}, "T56": {"supportedConfigurations": ["K19", "K35", "K1", "K23", "K3", "K22", "K24", "K29", "K31", "K34", "K12", "K18", "K5", "K4", "K28", "K27", "K6", "K30", "K9", "K11", "K17", "K21", "K26", "K14", "K13", "K16", "K8", "K7", "K20", "K32"]}, "T57": {"supportedConfigurations": ["K12", "K1", "K18", "K21", "K15", "K26", "K28", "K20", "K34", "K3", "K33", "K14", "K5", "K7", "K29", "K19", "K22", "K25", "K31", "K13", "K24", "K4", "K8", "K2", "K11", "K6", "K16", "K27"]}, "T58": {"supportedConfigurations": ["K1", "K17", "K20", "K5", "K4", "K10", "K9", "K30", "K6", "K31", "K2", "K7", "K11", "K28", "K23", "K34", "K12", "K3", "K18", "K8", "K15", "K19", "K14", "K22", "K24", "K13", "K35", "K25", "K33", "K29", "K27", "K32", "K21", "K16"]}, "T59": {"supportedConfigurations": ["K33", "K19", "K34", "K6", "K11", "K35", "K24", "K20", "K22", "K1", "K21", "K2", "K18", "K4", "K31", "K17", "K3", "K5", "K23", "K14", "K16", "K30", "K10", "K25", "K8", "K26", "K28", "K7"]}, "T60": {"supportedConfigurations": ["K34", "K13", "K21", "K10", "K4", "K19", "K8", "K29", "K20", "K14", "K22", "K26", "K35", "K23", "K27", "K31", "K5", "K16", "K11", "K7", "K3", "K30", "K28", "K15", "K6"]}, "T61": {"supportedConfigurations": ["K31", "K12", "K21", "K13", "K23", "K14", "K2", "K10", "K11", "K18", "K28", "K17", "K7", "K22", "K27"]}, "T62": {"supportedConfigurations": ["K17", "K31", "K21", "K29", "K11", "K15", "K19", "K26", "K1", "K18", "K9", "K5", "K33", "K16", "K2", "K7", "K25", "K27", "K8", "K34", "K35", "K20", "K32", "K30", "K22", "K13", "K12", "K3", "K14", "K23", "K28", "K10"]}, "T63": {"supportedConfigurations": ["K34", "K33", "K8", "K13", "K18", "K15", "K23", "K14", "K9", "K6", "K31", "K19", "K25"]}, "T64": {"supportedConfigurations": ["K25", "K19", "K24", "K18", "K4", "K6", "K7", "K26", "K8", "K31", "K29", "K27", "K35", "K13", "K15", "K32", "K17", "K33", "K12", "K5", "K30", "K1", "K20"]}, "T65": {"supportedConfigurations": ["K26", "K10", "K2", "K20", "K8", "K34"]}, "T66": {"supportedConfigurations": ["K34", "K22", "K15", "K2", "K21", "K10", "K3", "K5", "K1", "K32", "K6", "K16", "K25", "K19", "K30", "K9", "K28", "K12", "K7", "K17"]}, "T67": {"supportedConfigurations": ["K8", "K27", "K32", "K22", "K17"]}, "T68": {"supportedConfigurations": ["K35", "K5", "K29", "K34", "K32", "K15", "K13", "K18", "K20"]}, "T69": {"supportedConfigurations": ["K5", "K28", "K6", "K35", "K30", "K2", "K10", "K20", "K21", "K16", "K7", "K27", "K4", "K11", "K14", "K1", "K18", "K13", "K17", "K12", "K8", "K23", "K24", "K31", "K19", "K26", "K33", "K15", "K22", "K25", "K34", "K32", "K29", "K9", "K3"]}, "T70": {"supportedConfigurations": ["K29", "K24", "K5", "K30", "K14", "K33", "K6", "K15", "K2", "K34", "K27", "K16", "K9", "K11", "K22", "K25", "K17", "K3", "K18", "K7", "K35"]}, "T71": {"supportedConfigurations": ["K1", "K14", "K4"]}, "T72": {"supportedConfigurations": ["K15", "K30", "K24", "K29", "K10", "K14", "K9", "K34", "K17", "K12", "K7", "K26", "K13", "K23", "K25", "K4", "K16", "K19", "K8", "K28", "K5"]}, "T73": {"supportedConfigurations": ["K19", "K14", "K4", "K20", "K6", "K13", "K8", "K27", "K28", "K26", "K31", "K16", "K33", "K10", "K7", "K34", "K1", "K15", "K5", "K18", "K3", "K24", "K21", "K25", "K9", "K22", "K29", "K23", "K11", "K2", "K32"]}, "T74": {"supportedConfigurations": ["K29", "K3", "K10", "K34", "K31", "K7", "K23", "K20", "K2", "K32", "K21", "K15", "K30", "K11", "K8", "K5", "K24", "K1", "K14", "K18", "K35", "K13", "K4", "K12", "K27"]}, "T75": {"supportedConfigurations": ["K24", "K15", "K1", "K35", "K4", "K29", "K6", "K19", "K28", "K17", "K3", "K20", "K23", "K32", "K31", "K30", "K25", "K27", "K5", "K14", "K26", "K12", "K18", "K21", "K16", "K33", "K8", "K7"]}, "T76": {"supportedConfigurations": ["K25", "K2", "K17", "K1", "K19", "K10", "K29", "K24", "K30", "K23", "K7"]}, "T77": {"supportedConfigurations": ["K19", "K21", "K9", "K16", "K12", "K25", "K14", "K24", "K20", "K22", "K33", "K11", "K29", "K26", "K18"]}, "T78": {"supportedConfigurations": ["K25", "K9", "K18", "K35", "K1", "K15", "K27"]}, "T79": {"supportedConfigurations": ["K35", "K21", "K12", "K8"]}, "T80": {"supportedConfigurations": ["K33", "K27", "K34", "K28", "K1", "K32", "K9", "K31", "K13", "K11", "K15", "K17", "K5", "K35", "K22", "K8", "K10", "K24", "K26", "K6", "K20", "K19"]}, "T81": {"supportedConfigurations": ["K4", "K11", "K9", "K16", "K1", "K2", "K10", "K22", "K20", "K32", "K5", "K14", "K15", "K8", "K21", "K12", "K35", "K25", "K34", "K13", "K19", "K30", "K26", "K23", "K27", "K29", "K3", "K33", "K7", "K6", "K28", "K18", "K17", "K31"]}, "T82": {"supportedConfigurations": ["K3", "K18", "K27", "K24"]}, "T83": {"supportedConfigurations": ["K2", "K32", "K9", "K20", "K33", "K14", "K31", "K16", "K22", "K21", "K13", "K26", "K23", "K8", "K17", "K35", "K7", "K25", "K24", "K10", "K30", "K34", "K3", "K15", "K28"]}, "T84": {"supportedConfigurations": ["K4", "K21", "K14", "K18", "K11", "K35", "K12", "K5", "K13", "K27", "K28", "K17", "K8", "K7", "K34", "K1", "K29", "K2", "K24", "K33", "K20", "K3", "K10", "K15", "K9"]}, "T85": {"supportedConfigurations": ["K4", "K13", "K14", "K8", "K1", "K26", "K15", "K19", "K24", "K25", "K18", "K21", "K9", "K20", "K31", "K12", "K16", "K5", "K28", "K6", "K29"]}, "T86": {"supportedConfigurations": ["K10", "K30", "K2", "K22", "K26", "K11", "K20", "K29", "K5", "K32", "K12", "K7", "K24", "K4", "K31", "K19", "K1", "K13", "K9", "K16", "K35", "K34", "K25", "K17", "K28", "K18", "K8", "K23", "K15", "K14", "K3", "K33"]}, "T87": {"supportedConfigurations": ["K23", "K17", "K4", "K22", "K12", "K13", "K3", "K32", "K26", "K29", "K16", "K7", "K14", "K10", "K2", "K28", "K30", "K34", "K25", "K8", "K20", "K31", "K5", "K21", "K11", "K1", "K35", "K18", "K19", "K27", "K6", "K24", "K9", "K15", "K33"]}, "T88": {"supportedConfigurations": ["K7", "K2", "K11", "K28", "K25", "K30", "K16", "K5", "K1", "K20", "K14", "K13", "K22", "K34", "K35", "K33", "K12", "K19", "K9", "K8", "K26", "K17", "K24", "K15", "K6", "K23", "K21", "K29", "K3", "K27", "K10", "K31", "K4", "K32", "K18"]}, "T89": {"supportedConfigurations": ["K16", "K15", "K7", "K12", "K11", "K22", "K8", "K6", "K18", "K20", "K2", "K33"]}, "T90": {"supportedConfigurations": ["K13", "K30"]}, "T91": {"supportedConfigurations": ["K13", "K4", "K21", "K6", "K10", "K35", "K24", "K29", "K8", "K2", "K20", "K1", "K28", "K22", "K18", "K16", "K3", "K11", "K31", "K12", "K33", "K19", "K17", "K14", "K30"]}, "T92": {"supportedConfigurations": ["K5", "K35", "K4", "K6", "K18", "K13", "K30", "K21", "K29", "K24"]}, "T93": {"supportedConfigurations": ["K1", "K23", "K24", "K17", "K26", "K9", "K7", "K2", "K11", "K27", "K6", "K16", "K33", "K8", "K5", "K13", "K14", "K34", "K31", "K4", "K3"]}, "T94": {"supportedConfigurations": ["K24", "K34", "K1", "K28", "K13", "K32", "K15", "K11", "K30", "K7", "K17", "K22", "K18", "K19", "K23", "K25"]}, "T95": {"supportedConfigurations": ["K24", "K31", "K8", "K5", "K22", "K3", "K28", "K9", "K12", "K26", "K14", "K2", "K25", "K21", "K18"]}, "T96": {"supportedConfigurations": ["K16", "K27", "K33", "K29", "K2", "K4", "K28", "K9", "K34", "K23", "K21", "K15", "K8", "K3", "K20", "K1", "K12"]}, "T97": {"supportedConfigurations": ["K23", "K5", "K34", "K15", "K12", "K14", "K11", "K30", "K21", "K2", "K1", "K3", "K6", "K19", "K29", "K18", "K25", "K7", "K24", "K26", "K9", "K8", "K33", "K32", "K31"]}, "T98": {"supportedConfigurations": ["K16", "K23", "K31", "K6", "K35", "K5", "K19", "K8", "K29"]}, "T99": {"supportedConfigurations": ["K27", "K31", "K25", "K17", "K18", "K7", "K28", "K6", "K14", "K16", "K23", "K35", "K22", "K2", "K34", "K8", "K32", "K1", "K4", "K11", "K33", "K5", "K26", "K21", "K19", "K9", "K24", "K29", "K13", "K10", "K12", "K30", "K15"]}, "T100": {"supportedConfigurations": ["K7", "K25", "K10", "K20", "K14", "K26", "K16", "K21", "K24", "K3", "K11", "K1", "K28", "K17", "K4", "K30", "K34", "K8", "K33", "K22", "K15", "K13", "K23", "K5", "K27", "K19", "K2", "K6", "K32", "K35", "K18", "K9", "K12", "K31"]}, "T101": {"supportedConfigurations": ["K15", "K16", "K6", "K31", "K34", "K29"]}, "T102": {"supportedConfigurations": ["K14", "K24", "K9", "K27", "K20", "K26"]}, "T103": {"supportedConfigurations": ["K21", "K31", "K15", "K26", "K30", "K16", "K9", "K34", "K20", "K23", "K3", "K22", "K33"]}, "T104": {"supportedConfigurations": ["K34", "K2", "K25", "K35", "K30", "K1", "K17", "K11"]}, "T105": {"supportedConfigurations": ["K30", "K34", "K14", "K19", "K33", "K29", "K31", "K5", "K17", "K6", "K13", "K3"]}, "T106": {"supportedConfigurations": ["K15", "K7", "K22", "K18"]}, "T107": {"supportedConfigurations": ["K18", "K31", "K10", "K2", "K13", "K30", "K6", "K4", "K16", "K21", "K1", "K29", "K8", "K28", "K19", "K23", "K15", "K25", "K11", "K22", "K32", "K26", "K20", "K17", "K24", "K34"]}, "T108": {"supportedConfigurations": ["K28", "K16"]}, "T109": {"supportedConfigurations": ["K13", "K33", "K25", "K4", "K5", "K24", "K28", "K10", "K26", "K27", "K14", "K6", "K21", "K8", "K34", "K35", "K29", "K32", "K22"]}, "T110": {"supportedConfigurations": ["K26", "K17", "K13", "K18", "K25", "K16", "K23", "K6", "K10", "K11", "K9", "K2", "K30", "K4", "K1", "K29", "K19", "K31", "K24", "K14"]}, "T111": {"supportedConfigurations": ["K20", "K30", "K12", "K21", "K28", "K1", "K8", "K33", "K13", "K19", "K4", "K6", "K5", "K24", "K32", "K14", "K27", "K11", "K18", "K3", "K25", "K17", "K29", "K10", "K26", "K7", "K9", "K15", "K34"]}, "T112": {"supportedConfigurations": ["K9", "K28", "K3", "K34"]}, "T113": {"supportedConfigurations": ["K2", "K26", "K8", "K31", "K25", "K16"]}, "T114": {"supportedConfigurations": ["K17", "K32", "K1", "K7", "K34", "K12", "K16", "K14", "K21", "K5", "K4", "K31"]}, "T115": {"supportedConfigurations": ["K28", "K26", "K14", "K22", "K25", "K6", "K15", "K33", "K2", "K9", "K29", "K30", "K23", "K13", "K8", "K27", "K20", "K34", "K4", "K35", "K12", "K10", "K32", "K11", "K3", "K21", "K17", "K1", "K31", "K5", "K19", "K7", "K24"]}, "T116": {"supportedConfigurations": ["K28", "K30", "K21", "K10", "K16", "K24", "K7", "K23", "K9", "K17", "K25", "K15", "K14", "K18", "K5", "K22"]}, "T117": {"supportedConfigurations": ["K9", "K11", "K29", "K7", "K3", "K24", "K31", "K8", "K26", "K34", "K1", "K27", "K22", "K15", "K6", "K16", "K4", "K30", "K13", "K35", "K25", "K12", "K18", "K23", "K10", "K14", "K17", "K21", "K28", "K19", "K32"]}, "T118": {"supportedConfigurations": ["K23", "K24", "K11", "K8", "K19", "K31"]}, "T119": {"supportedConfigurations": ["K34", "K10", "K5", "K16", "K28", "K6", "K32", "K15", "K17", "K33", "K19", "K29", "K25", "K26", "K22", "K27", "K1", "K11", "K9", "K2", "K4", "K14", "K3", "K35"]}, "T120": {"supportedConfigurations": ["K25", "K28", "K17", "K10", "K2", "K15", "K35", "K1", "K21", "K34", "K13", "K11", "K30"]}, "T121": {"supportedConfigurations": ["K25", "K1", "K26", "K19", "K34", "K18", "K32", "K10", "K9", "K15", "K13", "K23", "K8", "K7", "K27", "K2", "K12", "K28", "K14", "K24", "K17", "K21", "K35", "K31", "K30", "K3", "K5", "K16", "K22", "K4", "K11"]}, "T122": {"supportedConfigurations": ["K5", "K15", "K4", "K12", "K1", "K31", "K30", "K6", "K21", "K3", "K28", "K7", "K18", "K34", "K14", "K23", "K33", "K10"]}, "T123": {"supportedConfigurations": ["K34", "K28", "K10", "K27", "K17", "K8", "K18", "K14", "K21", "K25", "K1", "K29", "K20"]}, "T124": {"supportedConfigurations": ["K5", "K11", "K4", "K20", "K10", "K19", "K22", "K32", "K15", "K25", "K21", "K24", "K3", "K16"]}, "T125": {"supportedConfigurations": ["K1", "K32", "K27", "K34", "K20", "K7", "K6", "K15", "K13", "K33", "K18", "K2"]}, "T126": {"supportedConfigurations": ["K5", "K16", "K23", "K13", "K25", "K32", "K14", "K24", "K26", "K8", "K19", "K15", "K11", "K9", "K12", "K20", "K10", "K17", "K33", "K35", "K22", "K28", "K34", "K27", "K18", "K7", "K21"]}, "T127": {"supportedConfigurations": ["K20", "K24", "K11", "K7", "K5", "K35", "K31", "K29", "K18", "K12", "K1", "K22", "K33", "K10", "K21", "K2", "K14"]}, "T128": {"supportedConfigurations": ["K4", "K9", "K8", "K10", "K24", "K30", "K12", "K20", "K18", "K17", "K28", "K16", "K15", "K5", "K22", "K27", "K13", "K34", "K31"]}, "T129": {"supportedConfigurations": ["K10", "K23", "K27", "K5", "K29", "K16", "K30", "K25", "K12", "K35", "K11", "K32", "K8", "K9", "K7", "K19", "K1", "K6", "K22", "K13", "K34", "K21", "K26", "K31", "K18", "K3", "K4"]}, "T130": {"supportedConfigurations": ["K31", "K20", "K15", "K2", "K18", "K26", "K4", "K35", "K30", "K11", "K17", "K3", "K12", "K32", "K25", "K9", "K21", "K23", "K19", "K14", "K28", "K5", "K6", "K27", "K1", "K7"]}, "T131": {"supportedConfigurations": ["K10", "K6", "K28", "K18", "K27", "K22", "K1", "K31", "K21", "K12", "K2", "K7", "K13", "K5", "K25", "K14", "K4", "K34", "K23", "K19", "K17", "K26", "K35", "K11", "K33", "K30", "K3"]}, "T132": {"supportedConfigurations": ["K30", "K15", "K5", "K7", "K6", "K35"]}, "T133": {"supportedConfigurations": ["K28", "K29", "K20", "K15"]}, "T134": {"supportedConfigurations": ["K3", "K14", "K22", "K8", "K5", "K29", "K25", "K18"]}, "T135": {"supportedConfigurations": ["K1", "K13", "K35", "K5", "K20", "K6", "K11"]}, "T136": {"supportedConfigurations": ["K11", "K10", "K35", "K23", "K30", "K7", "K26", "K17", "K20", "K31", "K32", "K22", "K2", "K16", "K29", "K12", "K4", "K28", "K9", "K5", "K6", "K21", "K15", "K19", "K34", "K14", "K1", "K3", "K8", "K27", "K25", "K24", "K13"]}, "T137": {"supportedConfigurations": ["K32", "K10", "K11", "K30", "K17", "K19", "K2", "K34", "K3", "K31", "K16", "K27", "K13", "K8", "K12", "K1", "K15", "K26", "K24", "K21", "K22", "K35", "K4", "K33", "K18", "K29", "K5", "K28", "K20"]}, "T138": {"supportedConfigurations": ["K34", "K35", "K22", "K3", "K17", "K30", "K8", "K14", "K21", "K5", "K29", "K31", "K2", "K16", "K28", "K26", "K11", "K15", "K20", "K10", "K25", "K1", "K23", "K32"]}, "T139": {"supportedConfigurations": ["K35", "K26", "K9", "K14"]}, "T140": {"supportedConfigurations": ["K16", "K31", "K25", "K11"]}, "T141": {"supportedConfigurations": ["K23", "K21", "K10", "K32", "K7", "K6", "K5", "K20", "K19", "K22", "K13", "K3", "K29", "K35", "K33", "K14", "K30", "K8", "K27", "K18", "K11"]}, "T142": {"supportedConfigurations": ["K25", "K10", "K1", "K5", "K34", "K19", "K18", "K7", "K8", "K32", "K23", "K29", "K20", "K17", "K26", "K21", "K35", "K27", "K13", "K28", "K9", "K2", "K16", "K30", "K24", "K31", "K33", "K22", "K12", "K4", "K14", "K11", "K6"]}, "T143": {"supportedConfigurations": ["K13", "K18", "K33", "K23", "K5", "K19", "K10", "K7", "K24", "K30", "K22", "K20", "K9", "K26", "K14", "K35", "K32", "K21", "K2", "K17", "K6", "K28", "K25", "K4", "K8", "K27", "K12"]}, "T144": {"supportedConfigurations": ["K1", "K26", "K5", "K30", "K24", "K3", "K21", "K4", "K6", "K22", "K12", "K8", "K35", "K25", "K10", "K28", "K23", "K7", "K32", "K17"]}, "T145": {"supportedConfigurations": ["K4", "K34", "K15", "K16"]}, "T146": {"supportedConfigurations": ["K19", "K1", "K5", "K35", "K4", "K12", "K29", "K11", "K2", "K27", "K3", "K18", "K9", "K34", "K20", "K16", "K23", "K31", "K33", "K32", "K7", "K13", "K15", "K24", "K30", "K21", "K26", "K14", "K22", "K28", "K25", "K17", "K8", "K10", "K6"]}, "T147": {"supportedConfigurations": ["K7", "K35", "K16", "K32", "K27", "K2", "K29", "K18", "K30", "K21", "K5", "K20", "K13", "K8", "K34", "K12", "K28", "K17", "K6"]}, "T148": {"supportedConfigurations": ["K17", "K10", "K21", "K29", "K20", "K31"]}, "T149": {"supportedConfigurations": ["K30", "K23", "K18", "K24", "K2", "K21", "K10", "K19", "K1", "K16", "K20", "K8", "K17", "K13", "K4", "K35", "K12", "K34", "K7", "K29", "K32", "K31", "K26", "K15", "K33", "K11", "K14", "K5", "K28", "K3", "K22", "K27", "K25", "K9"]}, "T150": {"supportedConfigurations": ["K18", "K23", "K26", "K9", "K5", "K32", "K29", "K24", "K30", "K35", "K19", "K6", "K27"]}, "T151": {"supportedConfigurations": ["K3", "K29", "K27", "K13", "K10", "K12", "K20", "K6", "K4", "K16", "K33", "K35", "K5", "K2", "K15", "K32", "K24", "K23", "K18", "K7"]}, "T152": {"supportedConfigurations": ["K24", "K12", "K35", "K25", "K16", "K15", "K2", "K4", "K27", "K31", "K14", "K34", "K23", "K10", "K21", "K26"]}, "T153": {"supportedConfigurations": ["K30", "K34", "K2", "K28", "K31"]}, "T154": {"supportedConfigurations": ["K12", "K5", "K13", "K27", "K22", "K19", "K11", "K4", "K31", "K7", "K18", "K1", "K16", "K26", "K30", "K6", "K28", "K32", "K21", "K24", "K23", "K34", "K8", "K10", "K35", "K17", "K25", "K33"]}, "T155": {"supportedConfigurations": ["K2", "K33", "K19", "K32", "K8", "K28", "K21", "K34", "K4", "K15", "K24", "K3", "K17", "K31", "K25", "K1", "K20", "K27", "K12", "K30", "K29", "K10"]}, "T156": {"supportedConfigurations": ["K29", "K20", "K6"]}, "T157": {"supportedConfigurations": ["K19", "K30", "K3", "K24", "K23", "K11", "K20", "K26", "K18"]}, "T158": {"supportedConfigurations": ["K14", "K29", "K34", "K7", "K33", "K21"]}, "T159": {"supportedConfigurations": ["K34", "K17", "K4", "K19", "K15", "K2", "K27", "K25", "K8", "K1", "K11", "K31", "K18", "K30", "K24", "K21", "K20"]}, "T160": {"supportedConfigurations": ["K12", "K24", "K26", "K34", "K15", "K2", "K11", "K27", "K21", "K6", "K17", "K28", "K23", "K16", "K32", "K22", "K10", "K14", "K29", "K33", "K31", "K18", "K35", "K8", "K19", "K25", "K7", "K13", "K1", "K3", "K4", "K5", "K9"]}, "T161": {"supportedConfigurations": ["K16", "K18"]}, "T162": {"supportedConfigurations": ["K32", "K24", "K21", "K33", "K11", "K35", "K10", "K9", "K18", "K17", "K1", "K12", "K6", "K20", "K2", "K22", "K26", "K34", "K25", "K15", "K23", "K16", "K8", "K27", "K7", "K28", "K30", "K31", "K3"]}, "T163": {"supportedConfigurations": ["K18", "K22", "K13", "K28", "K4", "K27", "K35", "K6", "K12", "K10", "K31", "K14", "K15", "K19", "K5", "K33", "K7", "K17", "K9", "K11", "K29", "K23", "K26", "K16", "K30", "K2", "K32", "K20"]}, "T164": {"supportedConfigurations": ["K5", "K23", "K27", "K1", "K14", "K28", "K9", "K13", "K12", "K18", "K21", "K22", "K29", "K10", "K25", "K31", "K20", "K17", "K35", "K30", "K16", "K15", "K7", "K8"]}, "T165": {"supportedConfigurations": ["K1", "K17", "K15", "K6", "K23", "K20", "K28", "K3"]}, "T166": {"supportedConfigurations": ["K6", "K9", "K26", "K3", "K32", "K8", "K1", "K27", "K20", "K24", "K10", "K17", "K21", "K30", "K7", "K11", "K15", "K35", "K13", "K12", "K23", "K25", "K16", "K19", "K2", "K34", "K18", "K5", "K33", "K14", "K31"]}, "T167": {"supportedConfigurations": ["K33", "K12", "K1", "K8", "K6"]}, "T168": {"supportedConfigurations": ["K19", "K6", "K22", "K34", "K16", "K30", "K17", "K33", "K2", "K13", "K28", "K23", "K26", "K10", "K3", "K14"]}, "T169": {"supportedConfigurations": ["K4", "K13", "K28", "K11", "K19", "K24", "K16", "K10", "K17", "K31", "K25"]}, "T170": {"supportedConfigurations": ["K5", "K26", "K13", "K35", "K16", "K22", "K23", "K8", "K18", "K4", "K9", "K34", "K1", "K33", "K30"]}, "T171": {"supportedConfigurations": ["K30", "K3", "K20", "K34", "K26", "K13", "K8", "K15", "K10"]}, "T172": {"supportedConfigurations": ["K30", "K7", "K8", "K35", "K32", "K21", "K3", "K18", "K14", "K1", "K19", "K9", "K6", "K34", "K5", "K26", "K12", "K10", "K23", "K22", "K29", "K20", "K16", "K28", "K11", "K15", "K17"]}, "T173": {"supportedConfigurations": ["K6", "K18"]}, "T174": {"supportedConfigurations": ["K4", "K10", "K11", "K28", "K35"]}, "T175": {"supportedConfigurations": ["K3", "K29", "K8", "K19", "K26", "K16", "K14", "K31", "K7", "K13", "K18", "K24", "K32", "K30", "K20", "K33", "K2", "K4", "K6", "K23", "K21", "K35", "K15"]}, "T176": {"supportedConfigurations": ["K24", "K29", "K1", "K21", "K34", "K16", "K35", "K22", "K28"]}, "T177": {"supportedConfigurations": ["K15", "K19", "K2"]}, "T178": {"supportedConfigurations": ["K25", "K1", "K24", "K10", "K28", "K7", "K32", "K34", "K22", "K35", "K21", "K23", "K13", "K33", "K31", "K8", "K26", "K27", "K11"]}, "T179": {"supportedConfigurations": ["K2", "K33", "K18", "K10", "K5", "K15", "K1", "K29", "K4", "K22", "K9", "K3", "K12", "K30", "K20", "K25", "K24", "K26", "K23", "K16", "K28", "K17", "K14"]}, "T180": {"supportedConfigurations": ["K3", "K27", "K22", "K6", "K32", "K30", "K31", "K9", "K1", "K20", "K5", "K12", "K21", "K15"]}, "T181": {"supportedConfigurations": ["K2", "K21", "K17", "K25", "K23", "K34", "K8", "K24", "K9", "K15", "K13", "K7", "K27"]}, "T182": {"supportedConfigurations": ["K25", "K23", "K26", "K32", "K9", "K7", "K27", "K12"]}, "T183": {"supportedConfigurations": ["K14", "K24", "K2", "K18", "K21", "K34", "K19", "K35", "K9", "K12", "K22", "K15", "K3", "K26", "K30", "K5", "K7", "K4", "K25", "K33", "K6", "K32", "K8", "K13", "K10", "K11", "K31", "K20", "K27"]}, "T184": {"supportedConfigurations": ["K32", "K14", "K30", "K31"]}, "T185": {"supportedConfigurations": ["K28", "K4", "K5", "K26", "K32", "K3", "K22", "K17", "K21", "K2", "K34", "K23", "K11", "K14", "K20", "K15", "K31", "K9", "K1", "K18", "K12", "K29", "K7", "K13", "K24", "K8", "K27", "K19", "K30"]}, "T186": {"supportedConfigurations": ["K3", "K27", "K1"]}, "T187": {"supportedConfigurations": ["K18", "K11", "K33", "K34", "K13", "K7", "K31"]}, "T188": {"supportedConfigurations": ["K18", "K20", "K30", "K13", "K29", "K6", "K4", "K21", "K28", "K10", "K1", "K31", "K7", "K35"]}, "T189": {"supportedConfigurations": ["K1", "K17"]}, "T190": {"supportedConfigurations": ["K34", "K29", "K25", "K8", "K27", "K19", "K22", "K5", "K2", "K18", "K28", "K31", "K14", "K1", "K23", "K32", "K21", "K4", "K15", "K11", "K16", "K20", "K9", "K26", "K30", "K12", "K7", "K35", "K10", "K13", "K33", "K24", "K3", "K6"]}, "T191": {"supportedConfigurations": ["K10", "K6", "K16", "K32", "K30", "K25", "K18", "K3", "K4", "K22", "K13", "K20", "K7"]}, "T192": {"supportedConfigurations": ["K2", "K16", "K23"]}, "T193": {"supportedConfigurations": ["K10", "K33", "K23", "K29", "K18", "K11", "K34", "K16", "K20", "K12", "K35", "K32", "K13", "K22", "K6", "K27", "K30", "K17", "K31", "K1", "K19", "K14", "K24", "K4", "K3"]}, "T194": {"supportedConfigurations": ["K18", "K35", "K1", "K27", "K14", "K21", "K8", "K31", "K13", "K4", "K30", "K10", "K20", "K16", "K25", "K5", "K29", "K19", "K12", "K34", "K26", "K6", "K17", "K15", "K3", "K33", "K22", "K24", "K9", "K23", "K2", "K7"]}, "T195": {"supportedConfigurations": ["K35", "K18", "K1", "K32", "K15", "K14", "K33", "K9", "K11", "K21", "K7", "K6", "K30", "K2", "K20", "K17", "K26", "K29", "K34", "K23", "K4", "K25", "K3", "K16", "K27", "K5", "K28", "K22", "K13", "K31", "K12", "K10", "K8", "K24"]}, "T196": {"supportedConfigurations": ["K9", "K21", "K14", "K7", "K10", "K24", "K28", "K16", "K34", "K32", "K8", "K4", "K23", "K15", "K3", "K35", "K2", "K1", "K33", "K12", "K13", "K20"]}}}, "operations": {"count": 7, "items": {"O1": {"estimatedTestTime": {"K23": {"distribution": "normal", "mean": 81.45112093503788, "std": 4.072357653984325}, "K21": {"distribution": "normal", "mean": 175.1317028428337, "std": 2.0661140289790265}, "K35": {"distribution": "normal", "mean": 103.13838868638648, "std": 3.5634075494338933}, "K14": {"distribution": "normal", "mean": 5.903587252694373, "std": 2.0968437400904945}, "K7": {"distribution": "normal", "mean": 93.71848178347027, "std": 3.689766630052148}, "K4": {"distribution": "normal", "mean": 177.41243249002832, "std": 3.895904178203444}, "K25": {"distribution": "normal", "mean": 160.9744411849139, "std": 3.4012114787976797}, "K8": {"distribution": "normal", "mean": 55.405237259935724, "std": 4.168461888024881}, "K31": {"distribution": "normal", "mean": 65.08882926318742, "std": 2.370668058883097}, "K34": {"distribution": "normal", "mean": 57.58297000907053, "std": 3.763578611501951}, "K16": {"distribution": "normal", "mean": 189.286499347274, "std": 2.6128113045818147}, "K15": {"distribution": "normal", "mean": 25.95557565222755, "std": 2.6128847713247603}}, "compatibleConfigurations": ["K23", "K21", "K35", "K14", "K7", "K4", "K25", "K8", "K31", "K34", "K16", "K15"]}, "O2": {"estimatedTestTime": {"K26": {"distribution": "normal", "mean": 169.02719479352075, "std": 4.839410706158993}, "K21": {"distribution": "normal", "mean": 55.99771582822616, "std": 4.439153772490009}, "K4": {"distribution": "normal", "mean": 157.87787049073668, "std": 4.4029173774092785}, "K10": {"distribution": "normal", "mean": 150.69909083514352, "std": 3.9836688292003553}, "K30": {"distribution": "normal", "mean": 61.48698830553451, "std": 2.9136097747410803}, "K8": {"distribution": "normal", "mean": 22.132466152176523, "std": 3.1030605411794685}, "K11": {"distribution": "normal", "mean": 19.168928487246312, "std": 4.327299733115933}, "K15": {"distribution": "normal", "mean": 111.91426364691065, "std": 3.614073891435522}, "K22": {"distribution": "normal", "mean": 180.9738733121781, "std": 4.3547745289986715}, "K23": {"distribution": "normal", "mean": 67.12031949399483, "std": 4.0578727089224165}, "K25": {"distribution": "normal", "mean": 199.69108151740596, "std": 2.9990697176928816}, "K5": {"distribution": "normal", "mean": 119.12496716655481, "std": 3.997848193356722}, "K33": {"distribution": "normal", "mean": 142.14674512491825, "std": 4.969246858426592}, "K17": {"distribution": "normal", "mean": 92.56929651944849, "std": 2.698143811153837}}, "compatibleConfigurations": ["K26", "K21", "K4", "K10", "K30", "K8", "K11", "K15", "K22", "K23", "K25", "K5", "K33", "K17"]}, "O3": {"estimatedTestTime": {"K23": {"distribution": "normal", "mean": 125.83886417019117, "std": 2.0109974062264144}, "K3": {"distribution": "normal", "mean": 183.53383400965444, "std": 3.0106925865258676}, "K6": {"distribution": "normal", "mean": 175.64517394273153, "std": 3.5047078298792096}, "K28": {"distribution": "normal", "mean": 20.818986896885196, "std": 3.692419143602841}, "K27": {"distribution": "normal", "mean": 112.48132568223241, "std": 2.469320849133649}, "K17": {"distribution": "normal", "mean": 76.76800896227725, "std": 4.17304796396879}, "K34": {"distribution": "normal", "mean": 44.47235379486551, "std": 2.225202900775062}, "K24": {"distribution": "normal", "mean": 191.90169435509202, "std": 2.300280492303098}}, "compatibleConfigurations": ["K23", "K3", "K6", "K28", "K27", "K17", "K34", "K24"]}, "O4": {"estimatedTestTime": {"K29": {"distribution": "normal", "mean": 118.33000095443707, "std": 2.9099523004278214}, "K31": {"distribution": "normal", "mean": 177.9711475189459, "std": 2.4612309685140077}, "K9": {"distribution": "normal", "mean": 54.499013845831676, "std": 2.9692337153053203}, "K4": {"distribution": "normal", "mean": 28.226192006105737, "std": 2.73713058950722}, "K18": {"distribution": "normal", "mean": 125.60932239561485, "std": 3.6423645862345193}, "K35": {"distribution": "normal", "mean": 53.697775130382304, "std": 4.378066948462648}, "K27": {"distribution": "normal", "mean": 105.89917349005876, "std": 3.879338199686513}, "K20": {"distribution": "normal", "mean": 136.97696572334405, "std": 4.962785426486053}, "K26": {"distribution": "normal", "mean": 89.98462443715472, "std": 4.044919361410722}, "K7": {"distribution": "normal", "mean": 59.523780408820684, "std": 2.038898172936687}, "K8": {"distribution": "normal", "mean": 112.24381519701225, "std": 2.5797118472770473}}, "compatibleConfigurations": ["K29", "K31", "K9", "K4", "K18", "K35", "K27", "K20", "K26", "K7", "K8"]}, "O5": {"estimatedTestTime": {"K33": {"distribution": "normal", "mean": 154.09961610124438, "std": 4.707774926878098}, "K16": {"distribution": "normal", "mean": 107.5475788714184, "std": 2.452062447853654}, "K6": {"distribution": "normal", "mean": 178.3277929172576, "std": 4.535266871504779}, "K23": {"distribution": "normal", "mean": 67.32281827233523, "std": 3.6570665284927504}, "K3": {"distribution": "normal", "mean": 144.5537731324089, "std": 3.5691505782359982}, "K28": {"distribution": "normal", "mean": 50.48285637064862, "std": 2.868889545370744}, "K30": {"distribution": "normal", "mean": 147.91041859201047, "std": 2.3947366005998796}, "K8": {"distribution": "normal", "mean": 84.9565344260528, "std": 3.0080297563750293}}, "compatibleConfigurations": ["K33", "K16", "K6", "K23", "K3", "K28", "K30", "K8"]}, "O6": {"estimatedTestTime": {"K27": {"distribution": "normal", "mean": 95.34543618777016, "std": 2.929063628735679}, "K24": {"distribution": "normal", "mean": 22.93495820711712, "std": 4.211201120057653}, "K32": {"distribution": "normal", "mean": 82.76647497237508, "std": 4.608046047380757}, "K6": {"distribution": "normal", "mean": 171.0884731860989, "std": 4.73234067922236}, "K19": {"distribution": "normal", "mean": 40.38626405998046, "std": 4.587003429661457}, "K26": {"distribution": "normal", "mean": 95.57798502124369, "std": 4.704418514861958}, "K31": {"distribution": "normal", "mean": 13.657539583884194, "std": 4.432463292781341}, "K34": {"distribution": "normal", "mean": 98.36835601363018, "std": 4.03306901497613}, "K2": {"distribution": "normal", "mean": 161.76393238376738, "std": 4.530750396935403}, "K15": {"distribution": "normal", "mean": 50.83417709502869, "std": 4.131760012450698}, "K4": {"distribution": "normal", "mean": 198.42087136112173, "std": 4.661846471890991}, "K11": {"distribution": "normal", "mean": 52.339458468581256, "std": 4.12328232454815}, "K3": {"distribution": "normal", "mean": 124.88610956174557, "std": 3.5631913537917126}}, "compatibleConfigurations": ["K27", "K24", "K32", "K6", "K19", "K26", "K31", "K34", "K2", "K15", "K4", "K11", "K3"]}, "O7": {"estimatedTestTime": {"K21": {"distribution": "normal", "mean": 88.25371031083291, "std": 2.6803561906807394}, "K25": {"distribution": "normal", "mean": 32.85636187542396, "std": 3.4311160886229053}, "K4": {"distribution": "normal", "mean": 41.55174943938331, "std": 3.269080947052642}, "K35": {"distribution": "normal", "mean": 165.56955320203076, "std": 3.9897814017351227}, "K11": {"distribution": "normal", "mean": 74.99986401508588, "std": 3.354941141497943}, "K23": {"distribution": "normal", "mean": 69.71936610261396, "std": 2.3671488510940377}, "K33": {"distribution": "normal", "mean": 130.12708340211242, "std": 2.2520964140484856}, "K20": {"distribution": "normal", "mean": 72.89959574204511, "std": 4.244281852156488}, "K13": {"distribution": "normal", "mean": 115.86877342487234, "std": 4.939788649453957}, "K7": {"distribution": "normal", "mean": 160.1940207821092, "std": 3.353045647908144}, "K27": {"distribution": "normal", "mean": 105.30128667101118, "std": 3.6962351744768998}, "K26": {"distribution": "normal", "mean": 98.3704816981115, "std": 4.7018381109968725}}, "compatibleConfigurations": ["K21", "K25", "K4", "K35", "K11", "K23", "K33", "K20", "K13", "K7", "K27", "K26"]}}}, "products": {"count": 3, "items": {"P1": {"index": 0, "arrival": 0, "quantity": 9, "duedate": 215.34963633449388, "operations": ["O4", "O5", "O7", "O3", "O2"], "dependencies": [[3, 0], [3, 2], [4, 1], [4, 2]]}, "P2": {"index": 1, "arrival": 6.167378189488173, "quantity": 18, "duedate": 314.5588069709642, "operations": ["O7", "O1", "O6", "O3", "O5", "O4", "O2"], "dependencies": [[2, 0], [3, 0], [3, 1], [4, 0], [5, 0], [5, 2], [5, 4], [6, 1], [6, 3]]}, "P3": {"index": 2, "arrival": 10.53235188399721, "quantity": 8, "duedate": 302.30152546802117, "operations": ["O3", "O4", "O6", "O2", "O1", "O5"], "dependencies": [[2, 1], [2, 0], [3, 1], [4, 2], [5, 0]]}}}}